intercom/__init__.py
intercom/broker.py
intercom/controller.py
intercom/minion.py
intercom/controllers/__init__.py
intercom/controllers/keystrokes.py
intercom/controllers/terminal.py
intercom/minions/__init__.py
intercom/minions/acc.py
intercom/minions/arduino.py
intercom/minions/arduino2.py
intercom/minions/mpd_minion.py
intercom/minions/pc.py
intercom/minions/pc_with_class.py
intercom/minions/tts_espeak.py
intercom/minions/wol.py
intercom/monitors/__init__.py
intercom/monitors/ez430.py
intercom/monitors/iwdump.py
Intercom-0.2.3.dist-info/DESCRIPTION.rst
Intercom-0.2.3.dist-info/METADATA
Intercom-0.2.3.dist-info/pydist.json
Intercom-0.2.3.dist-info/RECORD
Intercom-0.2.3.dist-info/top_level.txt
Intercom-0.2.3.dist-info/WHEEL
