Metadata-Version: 2.0
Name: Intercom
Version: 0.2.3
Summary: Messaging system for Home automation
Home-page: https://github.com/oksome/Intercom/
Author: OKso.me
Author-email: @okso.me
License: AGPLv3
Keywords: home automation zeromq intercom
Platform: UNKNOWN
Classifier: Development Status :: 3 - Alpha
Classifier: Environment :: Console
Classifier: Programming Language :: Python :: 3
Classifier: Operating System :: POSIX
Classifier: Operating System :: MacOS :: MacOS X
Classifier: Intended Audience :: End Users/Desktop
Classifier: Intended Audience :: Science/Research
Classifier: Intended Audience :: Manufacturing
Classifier: License :: OSI Approved :: GNU Affero General Public License v3
Classifier: Topic :: Home Automation
Requires-Dist: pyzmq
